sphinxcontrib/__init__.py
sphinxcontrib/needs/__init__.py
sphinxcontrib/needs/api/__init__.py
sphinxcontrib/needs/api/configuration.py
sphinxcontrib/needs/api/exceptions.py
sphinxcontrib/needs/api/need.py
sphinxcontrib/needs/builder.py
sphinxcontrib/needs/config.py
sphinxcontrib/needs/css/blank/blank.css
sphinxcontrib/needs/css/blank/styles.css
sphinxcontrib/needs/css/common.css
sphinxcontrib/needs/css/dark/dark.css
sphinxcontrib/needs/css/dark/layouts.css
sphinxcontrib/needs/css/dark/styles.css
sphinxcontrib/needs/css/grids.css
sphinxcontrib/needs/css/modern/layouts.css
sphinxcontrib/needs/css/modern/modern.css
sphinxcontrib/needs/css/modern/styles.css
sphinxcontrib/needs/defaults.py
sphinxcontrib/needs/diagrams_common.py
sphinxcontrib/needs/directives/__init__.py
sphinxcontrib/needs/directives/need.py
sphinxcontrib/needs/directives/needbar.py
sphinxcontrib/needs/directives/needextend.py
sphinxcontrib/needs/directives/needextract.py
sphinxcontrib/needs/directives/needfilter.py
sphinxcontrib/needs/directives/needflow.py
sphinxcontrib/needs/directives/needgantt.py
sphinxcontrib/needs/directives/needimport.py
sphinxcontrib/needs/directives/needimport_template.rst
sphinxcontrib/needs/directives/needlist.py
sphinxcontrib/needs/directives/needpie.py
sphinxcontrib/needs/directives/needsequence.py
sphinxcontrib/needs/directives/needservice.py
sphinxcontrib/needs/directives/needtable.py
sphinxcontrib/needs/directives/utils.py
sphinxcontrib/needs/environment.py
sphinxcontrib/needs/external_needs.py
sphinxcontrib/needs/filter_common.py
sphinxcontrib/needs/functions/__init__.py
sphinxcontrib/needs/functions/common.py
sphinxcontrib/needs/functions/functions.py
sphinxcontrib/needs/images/avatar.png
sphinxcontrib/needs/images/avatar.svg
sphinxcontrib/needs/images/feather_png/activity.png
sphinxcontrib/needs/images/feather_png/airplay.png
sphinxcontrib/needs/images/feather_png/alert-circle.png
sphinxcontrib/needs/images/feather_png/alert-octagon.png
sphinxcontrib_needs-0.7.9.dist-info/LICENSE
sphinxcontrib_needs-0.7.9.dist-info/WHEEL
sphinxcontrib_needs-0.7.9.dist-info/METADATA
sphinxcontrib_needs-0.7.9.dist-info/RECORD
