Metadata-Version: 2.1
Name: sphinxcontrib-needs
Version: 0.7.9
Summary: Sphinx needs extension for managing needs/requirements and specifications
Home-page: http://github.com/useblocks/sphinxcontrib-needs
License: MIT
Author: team useblocks
Author-email: info@useblocks.com
Requires-Python: >3.6.2,<4.0
Classifier: Development Status :: 5 - Production/Stable
Classifier: Framework :: Sphinx :: Extension
Classifier: Intended Audience :: Developers
Classifier: License :: OSI Approved :: MIT License
Classifier: Operating System :: OS Independent
Classifier: Programming Language :: Python
Classifier: Programming Language :: Python :: 3
Classifier: Programming Language :: Python :: 3.10
Classifier: Programming Language :: Python :: 3.6
Classifier: Programming Language :: Python :: 3.7
Classifier: Programming Language :: Python :: 3.8
Classifier: Programming Language :: Python :: 3.9
Classifier: Topic :: Documentation
Classifier: Topic :: Utilities
Provides-Extra: docs
Requires-Dist: jsonschema (==3.2.0)
Requires-Dist: matplotlib (>3.1.0)
Requires-Dist: requests (>=2.25.1,<3.0.0)
Requires-Dist: requests-file (>=1.5.1,<2.0.0)
Requires-Dist: sphinx (>2.2); python_version >= "3.7"
Requires-Dist: sphinx (>2.2,<=3.0); python_version >= "3.6" and python_version < "3.7"
Requires-Dist: sphinx-data-viewer (>=0.1.1,<0.2.0)
Project-URL: Documentation, https://sphinxcontrib-needs.readthedocs.io/en/latest/
Project-URL: Repository, http://github.com/useblocks/sphinxcontrib-needs
